{
	"animations": [
		{
			"loop": false,
			"offsets": [-51, -81],
			"anim": "idle",
			"fps": 24,
			"name": "idle",
			"indices": []
		},
		{
			"loop": false,
			"offsets": [253, -131],
			"anim": "singLEFT",
			"fps": 24,
			"name": "left",
			"indices": []
		},
		{
			"loop": false,
			"offsets": [-73, -110],
			"anim": "singRIGHT",
			"fps": 24,
			"name": "right",
			"indices": []
		},
		{
			"loop": false,
			"offsets": [-98, -20],
			"anim": "singUP",
			"fps": 24,
			"name": "up",
			"indices": []
		},
		{
			"loop": false,
			"offsets": [-2, -187],
			"anim": "singDOWN",
			"fps": 24,
			"name": "down",
			"indices": []
		}
	],
	"vocals_file": "",
	"no_antialiasing": false,
	"image": "characters/black stickfigure",
	"position": [50, 230],
	"healthicon": "face",
	"flip_x": false,
	"healthbar_colors": [161, 161, 161],
	"camera_position": [20, -20],
	"sing_duration": 6.1,
	"scale": 1.4,
	"_editor_isPlayer": false
}